LICENSE.txt
MANIFEST.in
README.rst
requirements-2.5.txt
requirements-2.6.txt
requirements-3.0.txt
requirements-3.1.txt
requirements.txt
setup.py
projectmill/__init__.py
projectmill/utils.py
py_projectmill.egg-info/PKG-INFO
py_projectmill.egg-info/SOURCES.txt
py_projectmill.egg-info/dependency_links.txt
py_projectmill.egg-info/entry_points.txt
py_projectmill.egg-info/top_level.txt